{"Scarlett":"Scarlett - Just wants Toast","Mitsu":"Mitsu - Bee Possession!","Kistrex":"Kistrex - Want a burger?","Duana":"Duana- Group hug!!!","Kirra":"Kirra- Opening up","Xoronma":"Xoronma- Filled with Darkness","Hiro":"Hiro - Ez RG, Stress Free","Tsu":"Jerry Will Be My Minion!","Asa":"Asa & Mittens","Stella":"Stella: Not a licensed Therapist","Angel":"Angel & Etymo - Dark Duo","Lily":"Lily Winds - Not Burger Time","Vast":"Vast - Tireless Tinkerer","Xah":"Xah - PARTY TIME!!!","Taiyo":"Taiyō - Hopeful Hero","Teri":"Ketsueki - Dead Man Walking","Psyshock":"Psyshock yay","Robot Girl":"Robot Girl"}